abseil_dll.dll
re2.cp311-win32.pyd
re2.dll
re2.pdb
pyre2_updated-0.3.9.post1.dist-info/METADATA
pyre2_updated-0.3.9.post1.dist-info/WHEEL
pyre2_updated-0.3.9.post1.dist-info/top_level.txt
pyre2_updated-0.3.9.post1.dist-info/RECORD
