Metadata-Version: 2.4
Name: pyre2-updated
Version: 0.3.9.post1
Summary: Python wrapper for Google's RE2 using Cython
Home-page: https://github.com/tyteen4a03/pyre2
Author: Timothy Choi
License: BSD-3-Clause
Classifier: Programming Language :: Cython
Classifier: Programming Language :: Python :: 3.9
Classifier: Programming Language :: Python :: 3.10
Classifier: Programming Language :: Python :: 3.11
Classifier: Programming Language :: Python :: 3.12
Classifier: Programming Language :: Python :: 3.13
Classifier: Intended Audience :: Developers
Classifier: Topic :: Software Development :: Libraries :: Python Modules
Requires-Python: >=3.9
Provides-Extra: doc
Requires-Dist: sphinx; extra == "doc"
Requires-Dist: sphinx_rtd_theme; extra == "doc"
Requires-Dist: sphinxcontrib-apidoc; extra == "doc"
Provides-Extra: test
Requires-Dist: pytest; extra == "test"
Provides-Extra: perf
Requires-Dist: regex; extra == "perf"
